py3d/__init__.py
py3d/core.py
py3d/viewer.html
py3d-0.1.91.dist-info/licenses/LICENSE
py3d-0.1.91.dist-info/METADATA
py3d-0.1.91.dist-info/WHEEL
py3d-0.1.91.dist-info/top_level.txt
py3d-0.1.91.dist-info/RECORD
