Metadata-Version: 2.4
Name: py3d
Version: 0.1.91
Summary: py3d is a pure and lightweight python library of 3d data structures and functions, which can deal with points, lines, planes and 3d meshes in batches, and also visualize them. All the actions can be done in a jupyter notebook.
Home-page: https://tumiz.github.io/py3d/
Author: Tumiz
Author-email: hh11698@163.com
License: GPL-3.0 License
Requires-Python: >=3.7.0
License-File: LICENSE
Requires-Dist: pillow
Requires-Dist: numpy
Dynamic: author
Dynamic: author-email
Dynamic: description
Dynamic: description-content-type
Dynamic: home-page
Dynamic: license
Dynamic: license-file
Dynamic: requires-dist
Dynamic: requires-python
Dynamic: summary
